100_Days_of_RTL/Day1.v
// Design and verify a 2:1 mux

module day1 (
    input a, b, sel,
    output out
);

    assign out = sel ? b : a;

endmodule

100_Days_of_RTL/Day1_tb.v
`timescale 1ns/1ps
`include "Day1.v"

module day1_tb;

    reg a, b, sel;
    wire out;

    day1 uut(a,b,sel,out);

    initial begin
        $dumpfile("Day1_tb.vcd");
        $dumpvars(0,day1_tb);
    end

    initial begin
        for (integer i = 0; i < 10 ; i = i + 1) begin
            #5
            a = $random;
            b = $random;
            sel = $random%2;
        end
    end

    initial $monitor("a=%b b=%b sel=%b out=%b", a, b, sel, out);

endmodule

100_Days_of_RTL/Day1_tb.vcd
$date
	Wed Sep 06 13:53:32 2023
$end
$version
	Icarus Verilog
$end
$timescale
	1ps
$end
$scope module day1_tb $end
$var wire 1 ! out $end
$var reg 1 " a $end
$var reg 1 # b $end
$var reg 1 $ sel $end
$scope module uut $end
$var wire 1 " a $end
$var wire 1 # b $end
$var wire 1 $ sel $end
$var wire 1 ! out $end
$upscope $end
$scope begin $ivl_for_loop0 $end
$var integer 32 % i [31:0] $end
$upscope $end
$upscope $end
$enddefinitions $end
$comment Show the parameter values. $end
$dumpall
$end
#0
$dumpvars
b0 %
x$
x#
x"
x!
$end
#5000
1!
b1 %
1$
1#
0"
#10000
b10 %
1"
#15000
0!
b11 %
0#
#20000
b100 %
#25000
b101 %
#30000
b110 %
0$
1#
0"
#35000
1!
b111 %
1"
#40000
b1000 %
0#
#45000
0!
b1001 %
1#
0"
#50000
1!
b1010 %
1$
1"
