100_Days_of_RTL/Day14.v
// Design and verify a parameterized fixed priority arbiter
// Output should be produced in a single cycle
// Output must be one-hot

module day14 (
    input [2:0] requests,
    output [2:0] grants
);
    /*
    always @(*) begin
        case (requests)
            3'b000: grants = 3'b000;
            3'b001: grants = 3'b001;
            3'b010: grants = 3'b010;
            3'b011: grants = 3'b001;
            3'b100: grants = 3'b100;
            3'b101: grants = 3'b001;
            3'b110: grants = 3'b010;
            3'b111: grants = 3'b001;
            default: grants = 3'bxxx;
        endcase
    end
    */
    
    assign grants[0] = requests[0];

    genvar i;
    always @(*) begin
        grants[0] = requests[0];
        for (i = 1; i <= 3; i = i + 1) begin
           grants[i] = requests[i] & ~(|grants(i-1:0));
        end
    end
endmodule

100_Days_of_RTL/Day14_tb.v
`timescale 1ns/1ns
`include "Day14.v"

module day14_tb;
    
    reg [2:0] requests;
    wire [2:0] grants;

    day14 uut(requests,grants);

    initial begin
        $dumpfile("Day14_tb.vcd");
        $dumpvars(0,day14_tb);
    end

    initial begin
        #5 requests = 0;
        #5 requests = 1;
        #5 requests = 2;
        #5 requests = 3;
        #5 requests = 4;
        #5 requests = 5;
        #5 requests = 6;
        #5 requests = 7;
        #5 requests = 8;
        #5 $finish;
    end

    initial $monitor("requests=%b grants=%b", requests, grants);

endmodule

100_Days_of_RTL/Day14_tb.vcd
$date
	Tue Sep 12 15:48:12 2023
$end
$version
	Icarus Verilog
$end
$timescale
	1ns
$end
$scope module day14_tb $end
$var wire 3 ! grants [2:0] $end
$var reg 3 " requests [2:0] $end
$scope module uut $end
$var wire 3 # requests [2:0] $end
$var reg 3 $ grants [2:0] $end
$upscope $end
$upscope $end
$enddefinitions $end
$comment Show the parameter values. $end
$dumpall
$end
#0
$dumpvars
bx $
bx #
bx "
bx !
$end
#5
b0 !
b0 $
b0 "
b0 #
#10
b1 !
b1 $
b1 "
b1 #
#15
b10 !
b10 $
b10 "
b10 #
#20
b1 !
b1 $
b11 "
b11 #
#25
b100 !
b100 $
b100 "
b100 #
#30
b1 !
b1 $
b101 "
b101 #
#35
b10 !
b10 $
b110 "
b110 #
#40
b1 !
b1 $
b111 "
b111 #
#45
b0 !
b0 $
b0 "
b0 #
