100_Days_of_RTL/Day2.v
// Design and verify various flavours of a D flip-flop

module day2 (
    input clk, rst, d,
    output reg q_no_rst, q_sync_rst, q_async_rst
);
    
    // No Reset
    always @(posedge clk) begin
        q_no_rst <= d;
    end

    // Synchronous Reset
    always @(posedge clk) begin
        if (rst) begin
            q_sync_rst <= 0;
        end
        else begin
            q_sync_rst <= d;
        end
    end

    // Asynchronous Reset
    always @(posedge clk or posedge rst) begin
        if (rst) begin
            q_async_rst <= 0;
        end
        else begin
            q_async_rst <= d;
        end
    end

endmodule

100_Days_of_RTL/Day2_tb.v
`timescale 1ns/1ns
`include "Day2.v"

module day2_tb;
    
    reg clk, rst, d;
    wire q_no_rst, q_sync_rst, q_async_rst;

    day2 uut(clk, rst, d, q_no_rst, q_sync_rst, q_async_rst);

    initial begin
        $dumpfile("Day2_tb.vcd");
        $dumpvars(0,day2_tb);
    end

    initial clk = 0;
    always #5 clk = ~clk;

    initial begin
        rst = 1'b1;
        d = 1'b0;
        @(posedge clk);
        rst = 1'b0;
        @(posedge clk);
        d = 1'b1;
        @(posedge clk);
        @(posedge clk);
        @(negedge clk);
        rst = 1'b1;
        @(posedge clk);
        @(posedge clk);
        rst = 1'b0;
        @(posedge clk);
        @(posedge clk);
        $finish();
    end

    initial $monitor("clk=%b rst=%b d=%b q_no_rst=%b q_sync_rst=%b q_async_rst=%b", clk, rst, d, q_no_rst, q_sync_rst, q_async_rst);

endmodule

100_Days_of_RTL/Day2_tb.vcd
$date
	Fri Sep 08 12:59:12 2023
$end
$version
	Icarus Verilog
$end
$timescale
	1ns
$end
$scope module day2_tb $end
$var wire 1 ! q_sync_rst $end
$var wire 1 " q_no_rst $end
$var wire 1 # q_async_rst $end
$var reg 1 $ clk $end
$var reg 1 % d $end
$var reg 1 & rst $end
$scope module uut $end
$var wire 1 $ clk $end
$var wire 1 % d $end
$var wire 1 & rst $end
$var reg 1 # q_async_rst $end
$var reg 1 " q_no_rst $end
$var reg 1 ! q_sync_rst $end
$upscope $end
$upscope $end
$enddefinitions $end
$comment Show the parameter values. $end
$dumpall
$end
#0
$dumpvars
1&
0%
0$
0#
x"
x!
$end
#5
0"
0!
0&
1$
#10
0$
#15
1#
1%
1$
#20
0$
#25
1"
1!
1$
#30
0$
#35
1$
#40
0#
1&
0$
#45
0!
1$
#50
0$
#55
1#
0&
1$
#60
0$
#65
1!
1$
