100_Days_of_RTL/Day4.v
/*
Design and verify a 8-bit ALU which supports the following encoded operations:

Encoding	Operation	Comment
3'b000	    ADD	        -
3'b001	    SUB	        -
3'b010	    SLL	        Vector a should left shift using bits 2:0 of vector b
3'b011	    LSR	        Vector a should right shift using bits 2:0 of vector b
3'b100	    AND	        -
3'b101	    OR	        -
3'b110	    XOR	        -
3'b111	    EQL	        Output should be 1 when equal otherwise 0
*/

module day4 (
    input [7:0] in1, in2,
    input [2:0] opcode,
    output reg [7:0] out
);
    
    parameter ADD = 3'b000;
    parameter SUB = 3'b001;
    parameter SLL = 3'b010;
    parameter LSR = 3'b011;
    parameter AND = 3'b100;
    parameter OR = 3'b101;
    parameter XOR = 3'b110;
    parameter EQL = 3'b111;

    always @(*) begin
        case (opcode)
            ADD: out = in1 + in2;
            SUB: out = in1 - in2;
            SLL: out = in1[7:0] << in2[2:0];
            LSR: out = in1[7:0] >> in2[2:0];
            AND: out = in1 & in2;
            OR: out = in1 | in2;
            XOR: out = in1 ^ in2;
            EQL: out = (in1 == in2) ? 1 : 0;
        endcase
    end

endmodule

100_Days_of_RTL/Day4_tb.v
`timescale 1ns/1ns
`include "Day4.v"

module day4_tb;
    
    reg [7:0] in1, in2; 
    reg [2:0] opcode;
    wire [7:0] out;

    day4 uut(in1,in2,opcode,out);

    initial begin
        $dumpfile("Day4_tb.vcd");
        $dumpvars(0,day4_tb);
    end

    initial begin
        in1 = $random;
        in2 = $random;
        opcode = 0;
    end

    initial begin
        #10 opcode = 1;
        #10 opcode = 2;
        #10 opcode = 3;
        #10 opcode = 4;
        #10 opcode = 5;
        #10 opcode = 6;
        #10 opcode = 7;
    end

    initial $monitor("in1=%b in2=%b opcode=%b out=%b", in1, in2, opcode, out);

endmodule

100_Days_of_RTL/Day4_tb.vcd
$date
	Fri Sep 08 16:22:06 2023
$end
$version
	Icarus Verilog
$end
$timescale
	1ns
$end
$scope module day4_tb $end
$var wire 8 ! out [7:0] $end
$var reg 8 " in1 [7:0] $end
$var reg 8 # in2 [7:0] $end
$var reg 3 $ opcode [2:0] $end
$scope module uut $end
$var wire 8 % in1 [7:0] $end
$var wire 8 & in2 [7:0] $end
$var wire 3 ' opcode [2:0] $end
$var parameter 3 ( ADD $end
$var parameter 3 ) AND $end
$var parameter 3 * EQL $end
$var parameter 3 + LSR $end
$var parameter 3 , OR $end
$var parameter 3 - SLL $end
$var parameter 3 . SUB $end
$var parameter 3 / XOR $end
$var reg 8 0 out [7:0] $end
$upscope $end
$upscope $end
$enddefinitions $end
$comment Show the parameter values. $end
$dumpall
b110 /
b1 .
b10 -
b101 ,
b11 +
b111 *
b100 )
b0 (
$end
#0
$dumpvars
b10100101 0
b0 '
b10000001 &
b100100 %
b0 $
b10000001 #
b100100 "
b10100101 !
$end
#10
b10100011 !
b10100011 0
b1 $
b1 '
#20
b1001000 !
b1001000 0
b10 $
b10 '
#30
b10010 !
b10010 0
b11 $
b11 '
#40
b0 !
b0 0
b100 $
b100 '
#50
b10100101 !
b10100101 0
b101 $
b101 '
#60
b110 $
b110 '
#70
b0 !
b0 0
b111 $
b111 '
