100_Days_of_RTL/Day7.v
// Design and verify a 4-bit linear feedback shift register where the bit[0] of the register is driven by the XOR of the LFSR register bit[1] and bit[3]

module day7 (
    input clk, rst,
    output [3:0] out
);
    
    reg [3:0] current, next;

    always @(posedge clk) begin
        if (rst) begin
            current <= 4'hE;
        end
        else begin
            current <= next;
        end
    end

    always @(*) begin
        next = {current[2:0],current[1] ^ current[3]};
    end

    assign out = current;

endmodule

100_Days_of_RTL/Day7_tb.v
`timescale 1ns/1ns
`include "Day7.v"

module day7_tb;
    
    reg clk, rst;
    wire [3:0] out;

    day7 uut(clk,rst,out);

    initial begin
        $dumpfile("Day7_tb.vcd");
        $dumpvars(0,day7_tb);
    end

    initial begin
        clk = 0;
        rst = 1;
    end

    always #5 clk = ~clk;

    initial #10 rst = 0;
    initial #100 $finish;

    initial $monitor("clk=%b rst=%b out=%b", clk, rst, out);

endmodule

100_Days_of_RTL/Day7_tb.vcd
$date
	Mon Sep 11 12:25:17 2023
$end
$version
	Icarus Verilog
$end
$timescale
	1ns
$end
$scope module day7_tb $end
$var wire 4 ! out [3:0] $end
$var reg 1 " clk $end
$var reg 1 # rst $end
$scope module uut $end
$var wire 1 " clk $end
$var wire 4 $ out [3:0] $end
$var wire 1 # rst $end
$var reg 4 % current [3:0] $end
$var reg 4 & next [3:0] $end
$upscope $end
$upscope $end
$enddefinitions $end
$comment Show the parameter values. $end
$dumpall
$end
#0
$dumpvars
bx &
bx %
bx $
1#
0"
bx !
$end
#5
b1100 &
b1110 !
b1110 $
b1110 %
1"
#10
0"
0#
#15
b1001 &
b1100 !
b1100 $
b1100 %
1"
#20
0"
#25
b11 &
b1001 !
b1001 $
b1001 %
1"
#30
0"
#35
b111 &
b11 !
b11 $
b11 %
1"
#40
0"
#45
b1111 &
b111 !
b111 $
b111 %
1"
#50
0"
#55
b1110 &
b1111 !
b1111 $
b1111 %
1"
#60
0"
#65
b1100 &
b1110 !
b1110 $
b1110 %
1"
#70
0"
#75
b1001 &
b1100 !
b1100 $
b1100 %
1"
#80
0"
#85
b11 &
b1001 !
b1001 $
b1001 %
1"
#90
0"
#95
b111 &
b11 !
b11 $
b11 %
1"
