100_Days_of_RTL/Day8.v
// Design and verify a parameterized binary to one-hot converter

module day8 (
    input [3:0] binary_in,
    output [15:0] one_hot_out
);
    
    assign one_hot_out = 1 << binary_in;

endmodule

100_Days_of_RTL/Day8_tb.v
`timescale 1ns/1ns
`include "Day8.v"

module day8_tb;
    
    reg [3:0] binary_in;
    wire [15:0] one_hot_out;

    day8 uut(binary_in,one_hot_out);

    initial begin
        $dumpfile("Day8_tb.vcd");
        $dumpvars(0,day8_tb);
    end

    initial begin
        for (integer i = 0; i <= 16 ; i = i + 1) begin
            #5 binary_in = 0;
            binary_in = binary_in + i;
        end
        $finish;
    end

    initial $monitor("binary_in=%b one_hot_out=%b", binary_in, one_hot_out);

endmodule

100_Days_of_RTL/Day8_tb.vcd
$date
	Mon Sep 11 12:44:12 2023
$end
$version
	Icarus Verilog
$end
$timescale
	1ns
$end
$scope module day8_tb $end
$var wire 16 ! one_hot_out [15:0] $end
$var reg 4 " binary_in [3:0] $end
$scope module uut $end
$var wire 4 # binary_in [3:0] $end
$var wire 16 $ one_hot_out [15:0] $end
$upscope $end
$scope begin $ivl_for_loop0 $end
$var integer 32 % i [31:0] $end
$upscope $end
$upscope $end
$enddefinitions $end
$comment Show the parameter values. $end
$dumpall
$end
#0
$dumpvars
b0 %
bx $
bx #
bx "
bx !
$end
#5
b1 %
b1 !
b1 $
b0 "
b0 #
#10
b10 %
b10 !
b10 $
b1 "
b1 #
#15
b11 %
b100 !
b100 $
b10 "
b10 #
#20
b100 %
b1000 !
b1000 $
b11 "
b11 #
#25
b101 %
b10000 !
b10000 $
b100 "
b100 #
#30
b110 %
b100000 !
b100000 $
b101 "
b101 #
#35
b111 %
b1000000 !
b1000000 $
b110 "
b110 #
#40
b1000 %
b10000000 !
b10000000 $
b111 "
b111 #
#45
b1001 %
b100000000 !
b100000000 $
b1000 "
b1000 #
#50
b1010 %
b1000000000 !
b1000000000 $
b1001 "
b1001 #
#55
b1011 %
b10000000000 !
b10000000000 $
b1010 "
b1010 #
#60
b1100 %
b100000000000 !
b100000000000 $
b1011 "
b1011 #
#65
b1101 %
b1000000000000 !
b1000000000000 $
b1100 "
b1100 #
#70
b1110 %
b10000000000000 !
b10000000000000 $
b1101 "
b1101 #
#75
b1111 %
b100000000000000 !
b100000000000000 $
b1110 "
b1110 #
#80
b10000 %
b1000000000000000 !
b1000000000000000 $
b1111 "
b1111 #
#85
b10001 %
b1 !
b1 $
b0 "
b0 #
