100_Days_of_RTL/Day9.v
// Design and verify a parameterized binary to gray code converter

module day9 #(parameter W = 3)(
    input [W-1:0] binary_in,
    output [W-1:0] gray_out
);

/*
    always @(*) begin
        case (binary_in)
            0: gray_out <= 3'b000;
            1: gray_out <= 3'b001;
            2: gray_out <= 3'b011;
            3: gray_out <= 3'b010;
            4: gray_out <= 3'b110;
            5: gray_out <= 3'b111;
            6: gray_out <= 3'b101;
            7: gray_out <= 3'b100;
        endcase
    end
*/

    assign gray_out[W-1] = binary_in[W-1];                    // MSB 100
    assign gray_out[W-2] = binary_in[W-2+1] ^ binary_in[W-2]; // 010
    assign gray_out[W-3] = binary_in[W-3+1] ^ binary_in[W-3]; // 001

endmodule

100_Days_of_RTL/Day9_tb.v
`timescale 1ns/1ns
`include "Day9.v"

module day9_tb;
    
    parameter W = 3;
    reg [W-1:0] binary_in;
    wire [W-1:0] gray_out;

    day9 #(W) uut(binary_in,gray_out);

    initial begin
        $dumpfile("Day9_tb.vcd");
        $dumpvars(0,day9_tb);
    end

    initial begin
        for (integer i = 0; i <= 2**W; i = i+1) begin
            #5 binary_in = 0;
            binary_in = binary_in + i;
        end
        $finish;
    end

    initial $monitor("binary_in=%b gray_out=%b", binary_in, gray_out);

endmodule

100_Days_of_RTL/Day9_tb.vcd
$date
	Mon Sep 11 13:47:04 2023
$end
$version
	Icarus Verilog
$end
$timescale
	1ns
$end
$scope module day9_tb $end
$var wire 3 ! gray_out [2:0] $end
$var parameter 32 " W $end
$var reg 3 # binary_in [2:0] $end
$scope module uut $end
$var wire 3 $ binary_in [2:0] $end
$var wire 3 % gray_out [2:0] $end
$var parameter 32 & W $end
$upscope $end
$scope begin $ivl_for_loop0 $end
$var integer 32 ' i [31:0] $end
$upscope $end
$upscope $end
$enddefinitions $end
$comment Show the parameter values. $end
$dumpall
b11 &
b11 "
$end
#0
$dumpvars
b0 '
bx %
bx $
bx #
bx !
$end
#5
b0 !
b0 %
b1 '
b0 #
b0 $
#10
b1 !
b1 %
b10 '
b1 #
b1 $
#15
b11 !
b11 %
b11 '
b10 #
b10 $
#20
b10 !
b10 %
b100 '
b11 #
b11 $
#25
b110 !
b110 %
b101 '
b100 #
b100 $
#30
b111 !
b111 %
b110 '
b101 #
b101 $
#35
b101 !
b101 %
b111 '
b110 #
b110 $
#40
b100 !
b100 %
b1000 '
b111 #
b111 $
#45
b0 !
b0 %
b1001 '
b0 #
b0 $
