Tasks/Task1/Task1.v
module task1 #(parameter WIDTH = 5) (
    input clk, en, ld, rst,
    input [WIDTH-1:0] cnt_in,
    output reg [WIDTH-1:0] cnt_out
);

    always @(posedge clk) begin
        if (rst) begin
            cnt_out <= 0;
        end
        else begin
            if (ld) begin
                cnt_out <= cnt_in;
            end
            else begin
                if (en) begin
                    cnt_out <= cnt_out + 1;
                end
            end
        end
    end

endmodule

Tasks/Task1/Task1_tb.v
`timescale 1ns/1ns
`include "Task1.v"

module task1_tb;

    parameter W = 5;
    reg clk, en, ld, rst;
    reg [W-1:0] cnt_in;
    wire [W-1:0] cnt_out;

    task1 #(W) uut(clk,en,ld,rst,cnt_in,cnt_out);

    initial begin
        $dumpfile("Task1_tb.vcd");
        $dumpvars(0,task1_tb);
    end

    initial begin
        clk = 0;
        en = 0;
        ld = 0;
        rst = 1;
    end

    always #5 clk = ~clk;
    
    initial begin
        #10 cnt_in = $random;
        #20 en = 1;
        #40 rst = 0;
        #80 ld = 1;
        #100 $finish;
    end

    initial $monitor("clk=%b en=%b ld=%b rst=%b cnt_in=%b cnt_out=%b",clk,en,ld,rst,cnt_in,cnt_out);

endmodule

Tasks/Task1/Task1_tb.vcd
$date
	Fri Sep 08 15:45:36 2023
$end
$version
	Icarus Verilog
$end
$timescale
	1ns
$end
$scope module task1_tb $end
$var wire 5 ! cnt_out [4:0] $end
$var parameter 32 " W $end
$var reg 1 # clk $end
$var reg 5 $ cnt_in [4:0] $end
$var reg 1 % en $end
$var reg 1 & ld $end
$var reg 1 ' rst $end
$scope module uut $end
$var wire 1 # clk $end
$var wire 5 ( cnt_in [4:0] $end
$var wire 1 % en $end
$var wire 1 & ld $end
$var wire 1 ' rst $end
$var parameter 32 ) WIDTH $end
$var reg 5 * cnt_out [4:0] $end
$upscope $end
$upscope $end
$enddefinitions $end
$comment Show the parameter values. $end
$dumpall
b101 )
b101 "
$end
#0
$dumpvars
bx *
bx (
1'
0&
0%
bx $
0#
bx !
$end
#5
b0 !
b0 *
1#
#10
0#
b100 $
b100 (
#15
1#
#20
0#
#25
1#
#30
0#
1%
#35
1#
#40
0#
#45
1#
#50
0#
#55
1#
#60
0#
#65
1#
#70
0#
0'
#75
b1 !
b1 *
1#
#80
0#
#85
b10 !
b10 *
1#
#90
0#
#95
b11 !
b11 *
1#
#100
0#
#105
b100 !
b100 *
1#
#110
0#
#115
b101 !
b101 *
1#
#120
0#
#125
b110 !
b110 *
1#
#130
0#
#135
b111 !
b111 *
1#
#140
0#
#145
b1000 !
b1000 *
1#
#150
0#
1&
#155
b100 !
b100 *
1#
