half_adder.v
module half_adder 
(
    a,b,        // inputs
    sum,c_out    // outputs
);

    input  wire a,b;
    output wire sum,c_out;

    assign sum = a ^ b;
    assign c_out = a & b;
    
endmodule

full_adder_tb.v
`timescale 1ns/1ns
`include "half_adder.v"

module full_adder_tb;
    initial begin
        $dumpfile("full_adder_tb.vcd");
        $dumpvars(0,full_adder_tb);
    end

    reg  a_tb,b_tb,c_in_tb;
    wire sum1_tb,sum2_tb,c_out1_tb,c_out2_tb,c_out3_tb;
    
    half_adder half_adder2
    (
        .a(a_tb),
        .b(b_tb),
        .sum(sum1_tb),
        .c_out(c_out1_tb)
    );
    half_adder half_adder3
    (
        .a(sum1_tb),
        .b(c_in_tb),
        .sum(sum2_tb),
        .c_out(c_out2_tb)
    );

    initial begin
        a_tb = 1'b0;
        b_tb = 1'b0;
        c_in_tb = 1'b0;
        #5
        a_tb = 1'b0;
        b_tb = 1'b1;
        c_in_tb = 1'b0;
        #5
        a_tb = 1'b1;
        b_tb = 1'b0;
        c_in_tb = 1'b0;
        #5
        a_tb = 1'b1;
        b_tb = 1'b1;
        c_in_tb = 1'b0;
        #5
        a_tb = 1'b0;
        b_tb = 1'b0;
        c_in_tb = 1'b1;
        #5
        a_tb = 1'b0;
        b_tb = 1'b1;
        c_in_tb = 1'b1;
        #5
        a_tb = 1'b1;
        b_tb = 1'b0;
        c_in_tb = 1'b1;
        #5
        a_tb = 1'b1;
        b_tb = 1'b1;
        c_in_tb = 1'b1;
        #40
        $display("Test Completed!");
        $finish;
    end

    assign c_out3_tb = c_out1_tb | c_out2_tb;

endmodule

full_adder_tb.vcd
$date
	Mon May 10 12:46:15 2021
$end
$version
	Icarus Verilog
$end
$timescale
	1ns
$end
$scope module full_adder_tb $end
$var wire 1 ! c_out3_tb $end
$var wire 1 " sum2_tb $end
$var wire 1 # sum1_tb $end
$var wire 1 $ c_out2_tb $end
$var wire 1 % c_out1_tb $end
$var reg 1 & a_tb $end
$var reg 1 ' b_tb $end
$var reg 1 ( c_in_tb $end
$scope module half_adder2 $end
$var wire 1 & a $end
$var wire 1 ' b $end
$var wire 1 % c_out $end
$var wire 1 # sum $end
$upscope $end
$scope module half_adder3 $end
$var wire 1 # a $end
$var wire 1 ( b $end
$var wire 1 $ c_out $end
$var wire 1 " sum $end
$upscope $end
$upscope $end
$enddefinitions $end
#0
$dumpvars
0(
0'
0&
0%
0$
0#
0"
0!
$end
#5
1"
1#
1'
#10
0'
1&
#15
0"
1!
0#
1%
1'
#20
0!
1"
0%
1(
0'
0&
#25
1!
0"
1$
1#
1'
#30
0'
1&
#35
1"
0$
0#
1%
1'
