Tasks/Task3_Challenge/Task3_Challenge.v
/*

Design a One-Way Traffic Control System:
> On RESET every light would be LOW
> RED light will remain HIGH for 30s after that YELLOW light would be HIGH
> YELLOW light will remain HIGH for 3s along with RED light after that GREEN light would be HIGH
> GREEN light will remain HIGH for 30s after that YELLOW light would be HIGH
> YELLOW light will remain HIGH for 3s after that RED light would be HIGH

*/

module task3_challenge (
    input clk,
    input rst,
    output reg red,
    output reg yellow,
    output reg green
);
    
    localparam DISABLE = 3'b000;
    localparam STOP = 3'b001;
    localparam READY_TO_GO = 3'b010;
    localparam GO = 3'b011;
    localparam READY_TO_STOP = 3'b100;

    reg [2:0] current_state, next_state;
    
    always @(posedge clk) begin
        if (rst) begin
            current_state <= DISABLE;
        end
        else begin
            current_state <= next_state;
        end
    end

    always @(*) begin
        case (current_state)
            DISABLE: begin
                red = 0;
                yellow = 0;
                green = 0;
                next_state <= STOP;
            end
            STOP: begin
                red = 1;
                yellow = 0;
                green = 0;
                next_state = READY_TO_GO;
            end
            READY_TO_GO: begin
                red = 1;
                yellow = 1;
                green = 0;
                next_state = GO;
            end
            GO: begin
                red = 0;
                yellow = 0;
                green = 1;
                next_state = READY_TO_STOP;
            end
            READY_TO_STOP: begin
                red = 0;
                yellow = 1;
                green = 0;
                next_state = STOP;
            end
            default: next_state <= DISABLE;
        endcase
    end

endmodule

Tasks/Task3_Challenge/Task3_Challenge_tb.v
`timescale 1ms/1ms
`include "Task3_Challenge.v"

module task3_challenge_tb;
    
    reg clk;
    reg rst;
    wire red;
    wire green;

    task3_challenge uut(clk,rst,red,yellow,green);

    initial begin
        $dumpfile("Task3_Challenge_tb.vcd");
        $dumpvars(0,task3_challenge_tb);
    end

    initial clk = 0;
    always #500 clk = ~clk;

    initial begin
        #1000 rst = 1;
        #9000 rst = 0;
        #50000 $finish;
    end

endmodule

Tasks/Task3_Challenge/Task3_Challenge_tb.vcd
$date
	Wed Oct 18 12:21:23 2023
$end
$version
	Icarus Verilog
$end
$timescale
	1ms
$end
$scope module task3_challenge_tb $end
$var wire 1 ! yellow $end
$var wire 1 " red $end
$var wire 1 # green $end
$var reg 1 $ clk $end
$var reg 1 % rst $end
$scope module uut $end
$var wire 1 $ clk $end
$var wire 1 % rst $end
$var reg 3 & current_state [2:0] $end
$var reg 1 # green $end
$var reg 3 ' next_state [2:0] $end
$var reg 1 " red $end
$var reg 1 ! yellow $end
$upscope $end
$upscope $end
$enddefinitions $end
#0
$dumpvars
bx '
bx &
x%
0$
x#
x"
x!
$end
#500
1$
#1000
0$
1%
#1500
b1 '
0#
0!
0"
b0 &
1$
#2000
0$
#2500
1$
#3000
0$
#3500
1$
#4000
0$
#4500
1$
#5000
0$
#5500
1$
#6000
0$
#6500
1$
#7000
0$
#7500
1$
#8000
0$
#8500
1$
#9000
0$
#9500
1$
#10000
0$
0%
#10500
b10 '
1"
b1 &
1$
#11000
0$
#11500
b11 '
1!
b10 &
1$
#12000
0$
#12500
b100 '
1#
0!
0"
b11 &
1$
#13000
0$
#13500
b1 '
0#
1!
b100 &
1$
#14000
0$
#14500
b10 '
0!
1"
b1 &
1$
#15000
0$
#15500
b11 '
1!
b10 &
1$
#16000
0$
#16500
b100 '
1#
0!
0"
b11 &
1$
#17000
0$
#17500
b1 '
0#
1!
b100 &
1$
#18000
0$
#18500
b10 '
0!
1"
b1 &
1$
#19000
0$
#19500
b11 '
1!
b10 &
1$
#20000
0$
#20500
b100 '
1#
0!
0"
b11 &
1$
#21000
0$
#21500
b1 '
0#
1!
b100 &
1$
#22000
0$
#22500
b10 '
0!
1"
b1 &
1$
#23000
0$
#23500
b11 '
1!
b10 &
1$
#24000
0$
#24500
b100 '
1#
0!
0"
b11 &
1$
#25000
0$
#25500
b1 '
0#
1!
b100 &
1$
#26000
0$
#26500
b10 '
0!
1"
b1 &
1$
#27000
0$
#27500
b11 '
1!
b10 &
1$
#28000
0$
#28500
b100 '
1#
0!
0"
b11 &
1$
#29000
0$
#29500
b1 '
0#
1!
b100 &
1$
#30000
0$
#30500
b10 '
0!
1"
b1 &
1$
#31000
0$
#31500
b11 '
1!
b10 &
1$
#32000
0$
#32500
b100 '
1#
0!
0"
b11 &
1$
#33000
0$
#33500
b1 '
0#
1!
b100 &
1$
#34000
0$
#34500
b10 '
0!
1"
b1 &
1$
#35000
0$
#35500
b11 '
1!
b10 &
1$
#36000
0$
#36500
b100 '
1#
0!
0"
b11 &
1$
#37000
0$
#37500
b1 '
0#
1!
b100 &
1$
#38000
0$
#38500
b10 '
0!
1"
b1 &
1$
#39000
0$
#39500
b11 '
1!
b10 &
1$
#40000
0$
#40500
b100 '
1#
0!
0"
b11 &
1$
#41000
0$
#41500
b1 '
0#
1!
b100 &
1$
#42000
0$
#42500
b10 '
0!
1"
b1 &
1$
#43000
0$
#43500
b11 '
1!
b10 &
1$
#44000
0$
#44500
b100 '
1#
0!
0"
b11 &
1$
#45000
0$
#45500
b1 '
0#
1!
b100 &
1$
#46000
0$
#46500
b10 '
0!
1"
b1 &
1$
#47000
0$
#47500
b11 '
1!
b10 &
1$
#48000
0$
#48500
b100 '
1#
0!
0"
b11 &
1$
#49000
0$
#49500
b1 '
0#
1!
b100 &
1$
#50000
0$
#50500
b10 '
0!
1"
b1 &
1$
#51000
0$
#51500
b11 '
1!
b10 &
1$
#52000
0$
#52500
b100 '
1#
0!
0"
b11 &
1$
#53000
0$
#53500
b1 '
0#
1!
b100 &
1$
#54000
0$
#54500
b10 '
0!
1"
b1 &
1$
#55000
0$
#55500
b11 '
1!
b10 &
1$
#56000
0$
#56500
b100 '
1#
0!
0"
b11 &
1$
#57000
0$
#57500
b1 '
0#
1!
b100 &
1$
#58000
0$
#58500
b10 '
0!
1"
b1 &
1$
#59000
0$
#59500
b11 '
1!
b10 &
1$
