Components/D_Flip_Flop.v
/*

Delay on Clock High

d   q   qn  Comments
--------------------
0   0   1   No Change
1   1   1   Delay

*/

module d_ff (
    input clk, rst, d,
    output reg q,
    output qn
);
    
    always @(posedge clk or negedge rst) begin
        if (!rst) begin
            q <= 0;
        end
        else begin
            q <= d;
        end
    end

    assign qn = ~q;

endmodule

Components/D_Flip_Flop_tb.v
`timescale 1ns/1ns
`include "D_Flip_Flop.v"

module d_ff_tb;
    
    reg clk, rst, d;
    wire q, qn;

    d_ff uut(clk,rst,d,q,qn);

    initial begin
        $dumpfile("D_Flip_Flop_tb.vcd");
        $dumpvars(0,d_ff_tb);
    end

    initial clk = 0;
    always #5 clk = ~clk;

    initial rst = 0;
    initial #10 rst = 1;

    initial #20 d = 0;
    always #10 d = ~d;

    initial #100 $finish;

    initial $monitor("clk=%b rst=%b d=%b q=%b qn=%b", clk, rst, d, q, qn);

endmodule

Components/D_Flip_Flop_tb.vcd
$date
	Wed Sep 20 15:30:49 2023
$end
$version
	Icarus Verilog
$end
$timescale
	1ns
$end
$scope module d_ff_tb $end
$var wire 1 ! qn $end
$var wire 1 " q $end
$var reg 1 # clk $end
$var reg 1 $ d $end
$var reg 1 % rst $end
$scope module uut $end
$var wire 1 # clk $end
$var wire 1 $ d $end
$var wire 1 ! qn $end
$var wire 1 % rst $end
$var reg 1 " q $end
$upscope $end
$upscope $end
$enddefinitions $end
#0
$dumpvars
0%
x$
0#
0"
1!
$end
#5
1#
#10
0#
1%
#15
x!
x"
1#
#20
0#
1$
#25
0!
1"
1#
#30
0#
0$
#35
1!
0"
1#
#40
0#
1$
#45
0!
1"
1#
#50
0#
0$
#55
1!
0"
1#
#60
0#
1$
#65
0!
1"
1#
#70
0#
0$
#75
1!
0"
1#
#80
0#
1$
#85
0!
1"
1#
#90
0#
0$
#95
1!
0"
1#
#100
0#
1$
