Components/Priority_Arbiter.v
/*

R0 is Lowest Priority
R2 is Highest Priority

Inputs are N 
Outputs are N

R2 R1 R0 G2 G1 G0
-----------------
0  0  0  0  0  0
0  0  1  0  0  1
0  1  0  0  1  0
0  1  1  0  0  1
1  0  0  1  0  0
1  0  1  0  0  1
1  1  0  0  1  0
1  1  1  0  0  1

*/

module priority_arbiter (
    input clk,
    input rst,
    input [2:0] requests,
    output reg [2:0] grants
);

    always @(posedge clk) begin
       if (rst) begin
        grants = 0;
       end
       else begin
        case (requests)
        3'b000: grants = 3'b000;
        3'b001: grants = 3'b001;
        3'b010: grants = 3'b010;
        3'b011: grants = 3'b001;
        3'b100: grants = 3'b100;
        3'b101: grants = 3'b001;
        3'b110: grants = 3'b010;
        3'b111: grants = 3'b001;
        default: grants = 0;
       endcase
       end
    end
    
endmodule

Components/Priority_Arbiter_tb.v
`timescale 1ns/1ns
`include "Priority_Arbiter.v"

module priority_arbiter_tb;
    
    reg clk;
    reg rst;
    reg [2:0] requests;
    wire [2:0] grants;

    priority_arbiter uut(clk,rst,requests,grants);

    initial begin
        $dumpfile("Priority_Arbiter_tb.vcd");
        $dumpvars(0,priority_arbiter_tb);
    end

    initial clk = 0;
    always #5 clk = ~clk;

    initial begin
        #10 rst = 1;
        #50 rst = 0;
        for (integer i = 0; i < 8; i = i + 1) begin
            #10 requests = i;
        end
        #100 $finish;
    end

    initial $monitor("clk=%b rst=%b requests=%b grants=%b", clk, rst, requests, grants);

endmodule

Components/Priority_Arbiter_tb.vcd
$date
	Thu Oct 12 15:16:40 2023
$end
$version
	Icarus Verilog
$end
$timescale
	1ns
$end
$scope module priority_arbiter_tb $end
$var wire 3 ! grants [2:0] $end
$var reg 1 " clk $end
$var reg 3 # requests [2:0] $end
$var reg 1 $ rst $end
$scope module uut $end
$var wire 1 " clk $end
$var wire 3 % requests [2:0] $end
$var wire 1 $ rst $end
$var reg 3 & grants [2:0] $end
$upscope $end
$scope begin $ivl_for_loop0 $end
$var integer 32 ' i [31:0] $end
$upscope $end
$upscope $end
$enddefinitions $end
#0
$dumpvars
bx '
bx &
bx %
x$
bx #
0"
bx !
$end
#5
b0 !
b0 &
1"
#10
0"
1$
#15
1"
#20
0"
#25
1"
#30
0"
#35
1"
#40
0"
#45
1"
#50
0"
#55
1"
#60
0"
b0 '
0$
#65
1"
#70
0"
b1 '
b0 #
b0 %
#75
1"
#80
0"
b10 '
b1 #
b1 %
#85
b1 !
b1 &
1"
#90
0"
b11 '
b10 #
b10 %
#95
b10 !
b10 &
1"
#100
0"
b100 '
b11 #
b11 %
#105
b1 !
b1 &
1"
#110
0"
b101 '
b100 #
b100 %
#115
b100 !
b100 &
1"
#120
0"
b110 '
b101 #
b101 %
#125
b1 !
b1 &
1"
#130
0"
b111 '
b110 #
b110 %
#135
b10 !
b10 &
1"
#140
0"
b1000 '
b111 #
b111 %
#145
b1 !
b1 &
1"
