Components/SR_Flip_Flop.v
/*

Set and Reset on Clock High

s   r   q   qn  Comments
------------------------
0   0   0   1   No Change
0   1   0   1   Reset
1   0   1   0   Set
1   1   x   x   Invalid

*/

module sr_ff (
    input clk, rst, s, r,
    output reg q, 
    output qn
);
    
    always @(posedge clk or negedge rst) begin
        if (!rst) begin
            q <= 0;
        end
        else begin
            if (~s && ~r) q <= q;   // No Change
            if (s && ~r) q <= 1;    // Set
            if (~s && r) q <= 0;    // Reset 
        end
    end

    assign qn = ~q;

endmodule

Components/SR_Flip_Flop_tb.v
`timescale 1ns/1ns
`include "SR_Flip_Flop.v"

module sr_ff_tb;
    
    reg clk, rst, s, r;
    wire q, qn;

    sr_ff uut(clk,rst,s,r,q,qn);

    initial begin
        $dumpfile("SR_Flip_Flop_tb.vcd");
        $dumpvars(0,sr_ff_tb);
    end

    initial clk = 0;
    always #5 clk = ~clk;

    initial rst = 0;

    initial begin
        #10 rst = 1;
        repeat (4) begin
            #10 s = 0; r = 0;
            #10 s = 0; r = 1;
            #10 s = 1; r = 0;
            #10 s = 1; r = 1;
        end
        #10 $finish;
    end

    initial $monitor("clk=%b rst=%b s=%b r=%b q=%b qn=%b", clk, rst, s, r, q, qn);

endmodule

Components/SR_Flip_Flop_tb.vcd
$date
	Fri Oct 13 14:44:20 2023
$end
$version
	Icarus Verilog
$end
$timescale
	1ns
$end
$scope module sr_ff_tb $end
$var wire 1 ! qn $end
$var wire 1 " q $end
$var reg 1 # clk $end
$var reg 1 $ r $end
$var reg 1 % rst $end
$var reg 1 & s $end
$scope module uut $end
$var wire 1 # clk $end
$var wire 1 ! qn $end
$var wire 1 $ r $end
$var wire 1 % rst $end
$var wire 1 & s $end
$var reg 1 " q $end
$upscope $end
$upscope $end
$enddefinitions $end
#0
$dumpvars
x&
0%
x$
0#
0"
1!
$end
#5
1#
#10
0#
1%
#15
1#
#20
0#
0$
0&
#25
1#
#30
0#
1$
#35
1#
#40
0#
0$
1&
#45
0!
1"
1#
#50
0#
1$
#55
1#
#60
0#
0$
0&
#65
1#
#70
0#
1$
#75
1!
0"
1#
#80
0#
0$
1&
#85
0!
1"
1#
#90
0#
1$
#95
1#
#100
0#
0$
0&
#105
1#
#110
0#
1$
#115
1!
0"
1#
#120
0#
0$
1&
#125
0!
1"
1#
#130
0#
1$
#135
1#
#140
0#
0$
0&
#145
1#
#150
0#
1$
#155
1!
0"
1#
#160
0#
0$
1&
#165
0!
1"
1#
#170
0#
1$
